{
  "2019": [
    {
      "location": {
        "address": "Wollbach"
      },
      "starttime": "2019-11-29",
      "title": "Adventskranzverkauf"
    },
    {
      "location": {
        "address": "Wollbach"
      },
      "starttime": "2019-12-07",
      "title": "Weihnachtsfeier"
    },
    {
      "location": {
        "address": "Wollbach",
        "name": "Kirche"
      },
      "starttime": "2019-12-15T17:00:00Z",
      "title": "Jugendvorspiel"
    }
  ],
  "2020": [
    {
      "location": {
        "address": "Wollbach",
        "name": "Kandertalhalle"
      },
      "starttime": "2020-01-06T19:00:00Z",
      "title": "Neujahrsempfang"
    },
    {
      "location": {
        "address": "Wollbach",
        "name": "Kandertalhalle"
      },
      "starttime": "2020-01-17",
      "endtime": "2020-01-19",
      "title": "Probewochenende"
    },
    {
      "location": {
        "address": "Wollbach",
        "name": "Kandertalhalle"
      },
      "starttime": "2020-01-31",
      "endtime": "2020-02-01",
      "title": "Jahreskonzert"
    },
    {
      "location": {
        "address": "Wollbach",
        "name": "Kandertalhalle"
      },
      "starttime": "2020-02-13T19:00:00Z",
      "title": "Generalversammlungen"
    },
    {
      "location": {
        "address": "Wollbach",
        "name": "Forsthof"
      },
      "starttime": "2020-06-12T20:00:00Z",
      "endtime": "2020-06-13",
      "title": "Forsthof Open-Air"
    },
    {
      "location": {
        "address": "Schwörstadt"
      },
      "starttime": "2020-07-06",
      "title": "Auftritt am Rheinfest"
    },
    {
      "location": {
        "address": "Oberrotweil"
      },
      "starttime": "2020-09-12",
      "title": "Auftritt am Winzerfest der Winzerkapelle"
    },
    {
      "location": {
        "address": "Wollbach"
      },
      "starttime": "2020-10-10",
      "title": "Sauserbummel"
    },
    {
      "location": {
        "address": "Wollbach"
      },
      "starttime": "2020-10-11",
      "title": "Herbstfest"
    }
  ]
}
