{
  "2022": [
    {
      "location": {
        "address": "Wollbach"
      },
      "starttime": "2022-10-08",
      "endtime": "2022-10-08",
      "title": "Sauserbummel"
    },
    {
      "location": {
        "address": "Wollbach"
      },
      "starttime": "2022-10-09",
      "endtime": "2022-10-09",
      "title": "Herbstfest 'mal anders' - Marschmusik"
    },
    {
      "location": {
        "address": "Wollbach"
      },
      "starttime": "2022-11-25",
      "endtime": "2022-11-25",
      "title": "Adventskranzverkauf"
    },
    {
      "location": {
        "name": "Kirche",
        "address": "Wollbach"
      },
      "starttime": "2022-12-04",
      "endtime": "2022-12-04",
      "title": "Jugendvorspiel"
    }
  ],
  "2023": [
    {
      "location": {
        "name": "Kandertalhalle",
        "address": "Wollbach"
      },
      "starttime": "2023-01-06T19:00:00Z",
      "endtime": "2023-01-06T21:00:00Z",
      "title": "Neujahrsempfang"
    },
    {
      "location": {
        "name": "Kandertalhalle",
        "address": "Wollbach"
      },
      "starttime": "2023-01-27",
      "endtime": "2023-01-28",
      "title": "Jahreskonzert"
    },
    {
      "location": {
        "address": "Wollbach"
      },
      "starttime": "2023-06-30",
      "endtime": "2023-07-01",
      "title": "Open Air"
    }
  ]
}
